fourdigits_cli/__init__.py
fourdigits_cli/__main__.py
fourdigits_cli/cli.py
fourdigits_cli/settings.py
fourdigits_cli/commands/__init__.py
fourdigits_cli/commands/docker.py
fourdigits_cli/commands/docker_compose.py
fourdigits_cli/commands/exonet.py
fourdigits_cli/commands/gitlab.py
fourdigits_cli/commands/help.py
fourdigits_cli/commands/mypy.py
fourdigits_cli/utils/__init__.py
fourdigits_cli/utils/docker.py
fourdigits_cli/utils/git.py
fourdigits_cli-1.33.0.dist-info/METADATA
fourdigits_cli-1.33.0.dist-info/WHEEL
fourdigits_cli-1.33.0.dist-info/entry_points.txt
fourdigits_cli-1.33.0.dist-info/top_level.txt
fourdigits_cli-1.33.0.dist-info/RECORD
