Metadata-Version: 2.4
Name: fourdigits-cli
Version: 1.33.0
Summary: FourDigits CLI tool
Requires-Python: >= 3.9
Requires-Dist: click~=8.1.3
Requires-Dist: tomli~=2.0.1
Requires-Dist: fabric~=3.2.2
Requires-Dist: packaging
Requires-Dist: requests
Requires-Dist: watchdog
Requires-Dist: exonetapi
Provides-Extra: dev
Requires-Dist: black; extra == "dev"
Requires-Dist: isort; extra == "dev"
Requires-Dist: flake8; extra == "dev"
Requires-Dist: pytest; extra == "dev"
Requires-Dist: pytest-check; extra == "dev"
Requires-Dist: pytest-cov; extra == "dev"
Dynamic: description
Dynamic: description-content-type
Dynamic: provides-extra
Dynamic: requires-dist
Dynamic: requires-python
Dynamic: summary
